exonetapi/Client.py
exonetapi/RequestBuilder.py
exonetapi/__init__.py
exonetapi/auth/Authenticator.py
exonetapi/auth/__init__.py
exonetapi/create_resource.py
exonetapi/exceptions/ValidationException.py
exonetapi/exceptions/__init__.py
exonetapi/result/Parser.py
exonetapi/result/__init__.py
exonetapi/structures/ApiResource.py
exonetapi/structures/ApiResourceIdentifier.py
exonetapi/structures/ApiResourceSet.py
exonetapi/structures/Relation.py
exonetapi/structures/Relationship.py
exonetapi/structures/__init__.py
exonetapi-5.1.0.dist-info/METADATA
exonetapi-5.1.0.dist-info/WHEEL
exonetapi-5.1.0.dist-info/licenses/LICENSE.md
exonetapi-5.1.0.dist-info/RECORD
