Metadata-Version: 2.4
Name: exonetapi
Version: 5.1.0
Summary: Library to interact with the Exonet API.
License-Expression: MIT
License-File: LICENSE.md
Keywords: async,client,exonet,exonetapi
Author: Exonet
Author-email: development@exonet.nl
Maintainer: Exonet
Maintainer-email: development@exonet.nl
Requires-Python: >=3.9
Classifier: Development Status :: 4 - Beta
Classifier: Intended Audience :: Developers
Classifier: License :: OSI Approved :: MIT License
Classifier: Natural Language :: English
Classifier: Programming Language :: Python :: 3.9
Classifier: Programming Language :: Python :: 3.10
Classifier: Programming Language :: Python :: 3.11
Classifier: Programming Language :: Python :: 3.12
Classifier: Programming Language :: Python :: 3.13
Classifier: Programming Language :: Python :: 3
Classifier: Topic :: Software Development :: Libraries :: Python Modules
Requires-Dist: inflection (==0.5.1)
Requires-Dist: requests (==2.32.4)
